Workbook

Sheet PL_Assumptions
A1: P&L Model — NovaTech Industries Inc.
A3: Parameter | B3: Value
A4: Gross Margin | B4: 0.5
A5: EBITDA Margin | B5: 0.25
A6: D&A % of Revenue | B6: 0.05
A7: Tax Rate | B7: 0.24
A8: Interest Expense (B IRR) | B8: 18.8

Sheet P&L
A1: Item | B1: Year 1 | C1: Year 2 | D1: Year 3 | E1: Year 4 | F1: Year 5
A2: Revenue (B IRR) | B2: 817.5 | C2: 891.08 | D2: 971.27 | E2: 1058.69 | F2: 1153.97
A3: Gross Profit | B3: =B2*PL_Assumptions!$B$4 | C3: =C2*PL_Assumptions!$B$4 | D3: =D2*PL_Assumptions!$B$4 | E3: =E2*PL_Assumptions!$B$4 | F3: =F2*PL_Assumptions!$B$4
A4: EBITDA | B4: =B2*PL_Assumptions!$B$5 | C4: =C2*PL_Assumptions!$B$5 | D4: =D2*PL_Assumptions!$B$5 | E4: =E2*PL_Assumptions!$B$5 | F4: =F2*PL_Assumptions!$B$5
A5: D&A | B5: =B2*PL_Assumptions!$B$6 | C5: =C2*PL_Assumptions!$B$6 | D5: =D2*PL_Assumptions!$B$6 | E5: =E2*PL_Assumptions!$B$6 | F5: =F2*PL_Assumptions!$B$6
A6: EBIT | B6: =B4-B5 | C6: =C4-C5 | D6: =D4-D5 | E6: =E4-E5 | F6: =F4-F5
A7: Interest Expense (B IRR) | B7: =PL_Assumptions!$B$8 | C7: =PL_Assumptions!$B$8 | D7: =PL_Assumptions!$B$8 | E7: =PL_Assumptions!$B$8 | F7: =PL_Assumptions!$B$8
A8: EBT | B8: =B6-B7 | C8: =C6-C7 | D8: =D6-D7 | E8: =E6-E7 | F8: =F6-F7
A9: Tax | B9: =IF(B8>0,B8*PL_Assumptions!$B$7,0) | C9: =IF(C8>0,C8*PL_Assumptions!$B$7,0) | D9: =IF(D8>0,D8*PL_Assumptions!$B$7,0) | E9: =IF(E8>0,E8*PL_Assumptions!$B$7,0) | F9: =IF(F8>0,F8*PL_Assumptions!$B$7,0)
A10: Net Income | B10: =B8-B9 | C10: =C8-C9 | D10: =D8-D9 | E10: =E8-E9 | F10: =F8-F9
