Workbook

Sheet Inputs
A1: Loan Amortization Schedule
A3: Parameter | B3: Value
A4: Principal (M IRR) | B4: 1000
A5: Annual Rate | B5: 0.24
A6: Term (months) | B6: 12
A7: Loan Type | B7: bullet

Sheet Schedule
A1: Month | B1: Payment | C1: Principal | D1: Interest | E1: Balance
A2: 1 | B2: =C2+D2 | C2: =IF(A2=Inputs!$B$6,Inputs!$B$4,0) | D2: =Inputs!$B$4*Inputs!$B$5/12 | E2: =Inputs!$B$4-C2
A3: 2 | B3: =C3+D3 | C3: =IF(A3=Inputs!$B$6,Inputs!$B$4,0) | D3: =Inputs!$B$4*Inputs!$B$5/12 | E3: =E2-C3
A4: 3 | B4: =C4+D4 | C4: =IF(A4=Inputs!$B$6,Inputs!$B$4,0) | D4: =Inputs!$B$4*Inputs!$B$5/12 | E4: =E3-C4
A5: 4 | B5: =C5+D5 | C5: =IF(A5=Inputs!$B$6,Inputs!$B$4,0) | D5: =Inputs!$B$4*Inputs!$B$5/12 | E5: =E4-C5
A6: 5 | B6: =C6+D6 | C6: =IF(A6=Inputs!$B$6,Inputs!$B$4,0) | D6: =Inputs!$B$4*Inputs!$B$5/12 | E6: =E5-C6
A7: 6 | B7: =C7+D7 | C7: =IF(A7=Inputs!$B$6,Inputs!$B$4,0) | D7: =Inputs!$B$4*Inputs!$B$5/12 | E7: =E6-C7
A8: 7 | B8: =C8+D8 | C8: =IF(A8=Inputs!$B$6,Inputs!$B$4,0) | D8: =Inputs!$B$4*Inputs!$B$5/12 | E8: =E7-C8
A9: 8 | B9: =C9+D9 | C9: =IF(A9=Inputs!$B$6,Inputs!$B$4,0) | D9: =Inputs!$B$4*Inputs!$B$5/12 | E9: =E8-C9
A10: 9 | B10: =C10+D10 | C10: =IF(A10=Inputs!$B$6,Inputs!$B$4,0) | D10: =Inputs!$B$4*Inputs!$B$5/12 | E10: =E9-C10
A11: 10 | B11: =C11+D11 | C11: =IF(A11=Inputs!$B$6,Inputs!$B$4,0) | D11: =Inputs!$B$4*Inputs!$B$5/12 | E11: =E10-C11
A12: 11 | B12: =C12+D12 | C12: =IF(A12=Inputs!$B$6,Inputs!$B$4,0) | D12: =Inputs!$B$4*Inputs!$B$5/12 | E12: =E11-C12
A13: 12 | B13: =C13+D13 | C13: =IF(A13=Inputs!$B$6,Inputs!$B$4,0) | D13: =Inputs!$B$4*Inputs!$B$5/12 | E13: =E12-C13
