Workbook

Sheet PL_Assumptions
A1: P&L Model — Company
A3: Parameter | B3: Value
A4: Gross Margin | B4: 0.4
A5: EBITDA Margin | B5: 0.25
A6: D&A % of Revenue | B6: 0.1
A7: Tax Rate | B7: 0.25
A8: Interest Expense (B IRR) | B8: 0

Sheet P&L
A1: Item | B1: Year 1 | C1: Year 2 | D1: Year 3
A2: Revenue (B IRR) | B2: 1150 | C2: 1322.5 | D2: 1520.87
A3: Gross Profit | B3: =B2*PL_Assumptions!$B$4 | C3: =C2*PL_Assumptions!$B$4 | D3: =D2*PL_Assumptions!$B$4
A4: EBITDA | B4: =B2*PL_Assumptions!$B$5 | C4: =C2*PL_Assumptions!$B$5 | D4: =D2*PL_Assumptions!$B$5
A5: D&A | B5: =B2*PL_Assumptions!$B$6 | C5: =C2*PL_Assumptions!$B$6 | D5: =D2*PL_Assumptions!$B$6
A6: EBIT | B6: =B4-B5 | C6: =C4-C5 | D6: =D4-D5
A7: Interest Expense (B IRR) | B7: =PL_Assumptions!$B$8 | C7: =PL_Assumptions!$B$8 | D7: =PL_Assumptions!$B$8
A8: EBT | B8: =B6-B7 | C8: =C6-C7 | D8: =D6-D7
A9: Tax | B9: =IF(B8>0,B8*PL_Assumptions!$B$7,0) | C9: =IF(C8>0,C8*PL_Assumptions!$B$7,0) | D9: =IF(D8>0,D8*PL_Assumptions!$B$7,0)
A10: Net Income | B10: =B8-B9 | C10: =C8-C9 | D10: =D8-D9
