Workbook

Sheet Assumptions
A1: Three-Statement Model — Assumptions
A3: Parameter | B3: Value
A4: Tax Rate | B4: 0.25
A5: Dividend Payout Ratio | B5: 0.3
A7: Opening Balance Sheet
A8: Item | B8: Value
A9: Cash | B9: 30
A10: Accounts Receivable | B10: 15
A11: Inventory | B11: 20
A12: PP&E (Net) | B12: 80
A13: Other Assets | B13: 5
A14: Accounts Payable | B14: 10
A15: Other Liabilities | B15: 10
A16: Equity | B16: 130
A17: Total Assets | B17: =SUM(B9:B13)
A18: Total Liabilities | B18: =B14+B15
A19: Total L + E | B19: =B18+B16
A21: Annual Inputs
A22: Item | B22: Year 1 | C22: Year 2 | D22: Year 3
A23: Revenue | B23: 100 | C23: 110 | D23: 121
A24: EBIT | B24: 20 | C24: 23 | D24: 26
A25: Interest Expense | B25: 5 | C25: 4.5 | D25: 4
A26: D&A | B26: 8 | C26: 9 | D26: 10
A27: CapEx | B27: 12 | C27: 13 | D27: 14
A28: Accounts Receivable | B28: 18 | C28: 20 | D28: 22
A29: Inventory | B29: 22 | C29: 24 | D29: 26
A30: Accounts Payable | B30: 12 | C30: 14 | D30: 16
A31: Total Debt | B31: 50 | C31: 45 | D31: 40
A32: Net Borrowing | B32: -5 | C32: -5 | D32: -5

Sheet Income Statement
A1: Income Statement
A3: Item | B3: Year 1 | C3: Year 2 | D3: Year 3
A4: Revenue | B4: =Assumptions!B23 | C4: =Assumptions!C23 | D4: =Assumptions!D23
A5: EBIT | B5: =Assumptions!B24 | C5: =Assumptions!C24 | D5: =Assumptions!D24
A6: Interest Expense | B6: =Assumptions!B25 | C6: =Assumptions!C25 | D6: =Assumptions!D25
A7: EBT (Earnings Before Tax) | B7: =B5-B6 | C7: =C5-C6 | D7: =D5-D6
A8: Tax | B8: =MAX(0,B7*Assumptions!$B$4) | C8: =MAX(0,C7*Assumptions!$B$4) | D8: =MAX(0,D7*Assumptions!$B$4)
A9: Net Income | B9: =B7-B8 | C9: =C7-C8 | D9: =D7-D8
A10: Dividends | B10: =IF(B9>0,MAX(0,B9*Assumptions!$B$5),0) | C10: =IF(C9>0,MAX(0,C9*Assumptions!$B$5),0) | D10: =IF(D9>0,MAX(0,D9*Assumptions!$B$5),0)
A11: Retained Earnings Addition | B11: =B9-B10 | C11: =C9-C10 | D11: =D9-D10

Sheet Cash Flow Statement
A1: Cash Flow Statement
A3: Item | B3: Year 1 | C3: Year 2 | D3: Year 3
A4: OPERATING
A5: Net Income | B5: ='Income Statement'!B9 | C5: ='Income Statement'!C9 | D5: ='Income Statement'!D9
A6: + D&A | B6: =Assumptions!B26 | C6: =Assumptions!C26 | D6: =Assumptions!D26
A7: - Change in Working Capital | B7: =(Assumptions!B28+Assumptions!B29-Assumptions!B30)-(Assumptions!$B$10+Assumptions!$B$11-Assumptions!$B$14) | C7: =(Assumptions!C28+Assumptions!C29-Assumptions!C30)-(Assumptions!B28+Assumptions!B29-Assumptions!B30) | D7: =(Assumptions!D28+Assumptions!D29-Assumptions!D30)-(Assumptions!C28+Assumptions!C29-Assumptions!C30)
A8: Operating Cash Flow | B8: =B5+B6-B7 | C8: =C5+C6-C7 | D8: =D5+D6-D7
A10: INVESTING
A11: Capital Expenditure | B11: =-Assumptions!B27 | C11: =-Assumptions!C27 | D11: =-Assumptions!D27
A12: Investing Cash Flow | B12: =B11 | C12: =C11 | D12: =D11
A14: FINANCING
A15: Net Borrowing | B15: =Assumptions!B32 | C15: =Assumptions!C32 | D15: =Assumptions!D32
A16: Dividends Paid | B16: =-'Income Statement'!B10 | C16: =-'Income Statement'!C10 | D16: =-'Income Statement'!D10
A17: Financing Cash Flow | B17: =B15+B16 | C17: =C15+C16 | D17: =D15+D16
A19: Net Change in Cash | B19: =B8+B12+B17 | C19: =C8+C12+C17 | D19: =D8+D12+D17
A20: Ending Cash Balance | B20: =Assumptions!$B$9+B19 | C20: =B20+C19 | D20: =C20+D19

Sheet Balance Sheet
A1: Balance Sheet
A3: Item | B3: Opening | C3: Year 1 | D3: Year 2 | E3: Year 3
A4: ASSETS
A5: Cash | B5: =Assumptions!$B$9 | C5: ='Cash Flow Statement'!B20 | D5: ='Cash Flow Statement'!C20 | E5: ='Cash Flow Statement'!D20
A6: Accounts Receivable | B6: =Assumptions!$B$10 | C6: =Assumptions!B28 | D6: =Assumptions!C28 | E6: =Assumptions!D28
A7: Inventory | B7: =Assumptions!$B$11 | C7: =Assumptions!B29 | D7: =Assumptions!C29 | E7: =Assumptions!D29
A8: PP&E (Net) | B8: =Assumptions!$B$12 | C8: =B8+Assumptions!B27-Assumptions!B26 | D8: =C8+Assumptions!C27-Assumptions!C26 | E8: =D8+Assumptions!D27-Assumptions!D26
A9: Other Assets | B9: =Assumptions!$B$13 | C9: =B9 | D9: =C9 | E9: =D9
A10: Total Assets | B10: =SUM(B5:B9) | C10: =SUM(C5:C9) | D10: =SUM(D5:D9) | E10: =SUM(E5:E9)
A12: LIABILITIES & EQUITY
A13: Accounts Payable | B13: =Assumptions!$B$14 | C13: =Assumptions!B30 | D13: =Assumptions!C30 | E13: =Assumptions!D30
A14: Total Debt | B14: 0 | C14: =Assumptions!B31 | D14: =Assumptions!C31 | E14: =Assumptions!D31
A15: Other Liabilities | B15: =Assumptions!$B$15 | C15: =B15 | D15: =C15 | E15: =D15
A16: Total Liabilities | B16: =B13+B14+B15 | C16: =C13+C14+C15 | D16: =D13+D14+D15 | E16: =E13+E14+E15
A17: Equity | B17: =Assumptions!$B$16 | C17: =B17+'Income Statement'!B11 | D17: =C17+'Income Statement'!C11 | E17: =D17+'Income Statement'!D11
A18: Total L + E | B18: =B16+B17 | C18: =C16+C17 | D18: =D16+D17 | E18: =E16+E17
A19: Balance Check (A - L&E) | B19: =B10-B18 | C19: =C10-C18 | D19: =D10-D18 | E19: =E10-E18

Sheet Summary
A1: Financial Model — Three-Statement Summary
A3: Item | B3: Year 1 | C3: Year 2 | D3: Year 3
A4: Revenue | B4: ='Income Statement'!B4 | C4: ='Income Statement'!C4 | D4: ='Income Statement'!D4
A5: EBIT | B5: ='Income Statement'!B5 | C5: ='Income Statement'!C5 | D5: ='Income Statement'!D5
A6: Net Income | B6: ='Income Statement'!B9 | C6: ='Income Statement'!C9 | D6: ='Income Statement'!D9
A8: Operating CF | B8: ='Cash Flow Statement'!B8 | C8: ='Cash Flow Statement'!C8 | D8: ='Cash Flow Statement'!D8
A9: Investing CF | B9: ='Cash Flow Statement'!B12 | C9: ='Cash Flow Statement'!C12 | D9: ='Cash Flow Statement'!D12
A10: Financing CF | B10: ='Cash Flow Statement'!B17 | C10: ='Cash Flow Statement'!C17 | D10: ='Cash Flow Statement'!D17
A11: Net Change in Cash | B11: ='Cash Flow Statement'!B19 | C11: ='Cash Flow Statement'!C19 | D11: ='Cash Flow Statement'!D19
A13: Total Assets | B13: ='Balance Sheet'!C10 | C13: ='Balance Sheet'!D10 | D13: ='Balance Sheet'!E10
A14: Total Liabilities | B14: ='Balance Sheet'!C16 | C14: ='Balance Sheet'!D16 | D14: ='Balance Sheet'!E16
A15: Equity | B15: ='Balance Sheet'!C17 | C15: ='Balance Sheet'!D17 | D15: ='Balance Sheet'!E17
A16: Balance Check | B16: ='Balance Sheet'!C19 | C16: ='Balance Sheet'!D19 | D16: ='Balance Sheet'!E19
